flask_undoredo.py
Flask_UndoRedo-1.0.0.dist-info/LICENSE
Flask_UndoRedo-1.0.0.dist-info/METADATA
Flask_UndoRedo-1.0.0.dist-info/WHEEL
Flask_UndoRedo-1.0.0.dist-info/top_level.txt
Flask_UndoRedo-1.0.0.dist-info/RECORD
