Metadata-Version: 2.1
Name: Flask-UndoRedo
Version: 1.0.0
Summary: Add undo/redo functionality for Flask applications using SQLAlchemy.
Home-page: UNKNOWN
Author: Zach Todd
Author-email: zchtodd@gmail.com
License: MIT
Platform: any
Classifier: Environment :: Web Environment
Classifier: Intended Audience :: Developers
Classifier: License :: OSI Approved :: BSD License
Classifier: Operating System :: OS Independent
Classifier: Programming Language :: Python
Classifier: Topic :: Internet :: WWW/HTTP :: Dynamic Content
Classifier: Topic :: Software Development :: Libraries :: Python Modules
Requires-Dist: Flask
Requires-Dist: SQLAlchemy
